filewalker/Controller.py
filewalker/__init__.py
filewalker/__main__.py
filewalker/args/Args.py
filewalker/args/__init__.py
filewalker/search/Search.py
filewalker/search/__init__.py
filewalker/types/FileType.py
filewalker/types/__init__.py
filewalker/util/Util.py
filewalker/util/__init__.py
filewalker-1.0.2.dist-info/LICENSE.md
filewalker-1.0.2.dist-info/METADATA
filewalker-1.0.2.dist-info/WHEEL
filewalker-1.0.2.dist-info/entry_points.txt
filewalker-1.0.2.dist-info/top_level.txt
filewalker-1.0.2.dist-info/RECORD
