Metadata-Version: 2.1
Name: filewalker
Version: 1.0.2
Summary: Searches hard drives/given path for files specified by file extension
Home-page: https://github.com/5f0ne/filewalker
Author: 5f0
License: MIT
Classifier: Operating System :: OS Independent 
Classifier: Programming Language :: Python :: 3 
Classifier: License :: OSI Approved :: MIT License 
License-File: LICENSE.md
